Metadata-Version: 2.1
Name: XAUTH
Version: 2.1.15
Summary: Package for xauth.ml
Home-page: UNKNOWN
Author: Psyro
Author-email: <mail@psyro.de>
License: UNKNOWN
Keywords: wrapper,apiwrapper,keylabs,auth,authsystem
Platform: UNKNOWN
Classifier: Development Status :: 1 - Planning
Classifier: Intended Audience :: Developers
Classifier: Programming Language :: Python :: 3
Classifier: Operating System :: Unix
Classifier: Operating System :: MacOS :: MacOS X
Classifier: Operating System :: Microsoft :: Windows
